quick_deployer_sdk/__init__.py
quick_deployer_sdk/client.py
quick_deployer_sdk/exceptions.py
quick_deployer_sdk/project.py
quick_deployer_sdk/server.py
quick_deployer_sdk-1.0.0.dist-info/licenses/LICENSE
quick_deployer_sdk-1.0.0.dist-info/METADATA
quick_deployer_sdk-1.0.0.dist-info/WHEEL
quick_deployer_sdk-1.0.0.dist-info/top_level.txt
quick_deployer_sdk-1.0.0.dist-info/RECORD
