Metadata-Version: 2.4
Name: quick-deployer-sdk
Version: 1.0.0
Summary: A Python SDK for the QuickDeployer API, supporting API interactions for project and server management.
Home-page: https://github.com/niravsutariya/python-quick-deployer-sdk
Author: Nirav Sutariya
Author-email: sutariya_nirav@yahoo.com
License: MIT
Project-URL: Homepage, https://github.com/niravsutariya/python-quick-deployer-sdk#readme
Project-URL: Repository, https://github.com/niravsutariya/python-quick-deployer-sdk.git
Keywords: quickdeployer,sdk,python,api
Classifier: Development Status :: 5 - Production/Stable
Classifier: Intended Audience :: Developers
Classifier: License :: OSI Approved :: MIT License
Classifier: Programming Language :: Python :: 3
Classifier: Programming Language :: Python :: 3.7
Classifier: Programming Language :: Python :: 3.8
Classifier: Programming Language :: Python :: 3.9
Classifier: Programming Language :: Python :: 3.10
Classifier: Programming Language :: Python :: 3.11
Classifier: Programming Language :: Python :: 3.12
Classifier: Programming Language :: Python :: 3.13
Classifier: Operating System :: OS Independent
Classifier: Topic :: Software Development :: Libraries :: Python Modules
Requires-Python: >=3.7
License-File: LICENSE
Requires-Dist: requests>=2.28.0
Dynamic: author
Dynamic: author-email
Dynamic: classifier
Dynamic: description
Dynamic: description-content-type
Dynamic: home-page
Dynamic: keywords
Dynamic: license
Dynamic: license-file
Dynamic: project-url
Dynamic: requires-dist
Dynamic: requires-python
Dynamic: summary
